topicsync/__init__.py
topicsync/change.py
topicsync/server/client_manager.py
topicsync/server/history_manager.py
topicsync/server/server.py
topicsync/server/update_buffer.py
topicsync/service.py
topicsync/state_machine/changes_tree.py
topicsync/state_machine/state_machine.py
topicsync/state_machine/transition_tree.py
topicsync/string_diff.py
topicsync/topic.py
topicsync/utils.py
topicsync_debugger/__init__.py
topicsync_debugger/debugger.py
topicsync_debugger/index.html
topicsync_debugger/main.js
topicsync_debugger/style.css
topicsync-0.13.0.dist-info/METADATA
topicsync-0.13.0.dist-info/WHEEL
topicsync-0.13.0.dist-info/RECORD
