Metadata-Version: 2.1
Name: topicsync
Version: 0.13.0
Summary: A communication tool for multi-client applications over WebSockets.
Author: eri24816
Author-email: a931eric@gmail.com
Maintainer: eri24816
Maintainer-email: a931eric@gmail.com
Requires-Python: >=3.11,<4.0
Classifier: Programming Language :: Python :: 3
Classifier: Programming Language :: Python :: 3.11
Requires-Dist: termcolor (>=2.3.0,<3.0.0)
Requires-Dist: websockets (>=11.0.3,<12.0.0)
